setup.py
scripts/vboxtrayico
vboxtrayico/__init__.py
vboxtrayico/core.py
vboxtrayico.egg-info/PKG-INFO
vboxtrayico.egg-info/SOURCES.txt
vboxtrayico.egg-info/dependency_links.txt
vboxtrayico.egg-info/top_level.txt