Metadata-Version: 1.1
Name: vboxtrayico
Version: 0.1.9
Summary: Virtualbox tray tool - list/start/stop VMs
Home-page: https://github.com/kAlmAcetA/vboxtrayico
Author: Krzysztof Warunek
Author-email: kalmaceta@gmail.com
License: MIT
Keywords: virtualbox tray vm pyside
Platform: UNKNOWN
Classifier: License :: OSI Approved :: MIT License
Classifier: Environment :: X11 Applications :: Qt
Classifier: Programming Language :: Python :: 3
Classifier: Programming Language :: Python :: 2
Classifier: Operating System :: Microsoft :: Windows
Classifier: Operating System :: POSIX
Classifier: Development Status :: 3 - Alpha
